vextra_utils/__init__.py
vextra_utils/_version.py
vextra_utils/decorators.py
vextra_utils/metaclasses.py
vextra_utils-1.0.1.dist-info/METADATA
vextra_utils-1.0.1.dist-info/WHEEL
vextra_utils-1.0.1.dist-info/licenses/LICENSE
vextra_utils-1.0.1.dist-info/RECORD
