Metadata-Version: 2.4
Name: vextra_utils
Version: 1.0.1
Summary: A collection of Python utilities for timing, concurrency control, thread safety, and design patterns.
Project-URL: Homepage, https://github.com/vnniciusg/vextra_utils
Project-URL: Repository, https://github.com/vnniciusg/vextra_utils
Project-URL: Issues, https://github.com/vnniciusg/vextra_utils/issues
License-File: LICENSE
Requires-Python: >=3.13
